physical/librelane/final_core/src/int_MAC.sv
`timescale 1ns / 1ps

module int_MAC(
    input logic i_clk,
    input logic i_rst_n,
    input logic i_valid,
    input logic signed [8:0] i_a,
    input logic signed [8:0] i_b,
    output logic o_valid,
    output logic signed [22:0] o_result,
    output logic o_overflow
);
    logic signed [17:0] product;
    logic valid_0;
    // logic [7:0] magn_a, magn_b;
    // logic signed [16:0] product_0;

    always_ff @(posedge i_clk or negedge i_rst_n) begin
        if (!i_rst_n) begin
            product <= 18'sd0;
            valid_0 <= 1'b0;
        end else begin
            if (i_valid) product <= $signed(i_a) * $signed(i_b);
            valid_0 <= i_valid;
        end
    end

    logic signed [23:0] extended_result; // For overflow detection
    logic signed [22:0] result_reg;
    logic overflow;

    always_ff @(posedge i_clk or negedge i_rst_n) begin
        if (!i_rst_n) begin
            result_reg <= 23'sd0;
            o_overflow <= 1'b0;
            o_valid <= 1'b0;
        end else begin
            if (valid_0 && !o_overflow) result_reg <= extended_result[22:0]; // Store the lower 23 bits of the extended result
            if (valid_0 && !o_overflow) o_overflow <= overflow;
            o_valid <= valid_0 && !o_overflow; // Output valid only if there is no overflow
        end
    end

    assign extended_result = $signed({result_reg[22], result_reg}) + $signed({{6{product[17]}}, product});
    assign overflow = extended_result[23] != extended_result[22]; // Check if the sign bit has changed
    assign o_result = result_reg;

endmodule

intMAC/INT_mac_TB.sv
`timescale 1ns / 1ps

module INT_mac_TB;
    // input
    logic clk;
    logic rst_n;
    logic valid;
    logic signed [8:0] a;
    logic signed [8:0] b;

    // output
    logic out_valid;
    logic signed [22:0] result;
    logic overflow;

  
    int_MAC mac_inst (
        .i_clk(clk),
        .i_rst_n(rst_n),
        .i_valid(valid),
        .i_a(a),
        .i_b(b),
        .o_valid(out_valid),
        .o_result(result),
        .o_overflow(overflow)
    );


    initial begin
        $dumpfile("mac.vcd");
        $dumpvars(0, INT_mac_TB);
    end


    initial clk = 0;
    always #5 clk = ~clk; // 100 MHz clock

    //localparam logic [1:0] VALID_SIGNS [0:2] = '{2'b00, 2'b01, 2'b11};

    initial begin
        $display("Time\tValid\tA\tB\tResult\tOut_Valid\tOverflow");
    end

    always @(posedge clk) begin
        $display("%0t\t%b\t%0d\t%0d\t%0d\t%b\t\t%b",
                 $time, valid, a, b, result, out_valid, overflow);
    end

    initial begin
        rst_n <= 0;
        valid <= 0;
        a <= 0;
        b <= 0;

        repeat (2) @(posedge clk);
        rst_n <= 1;

        // Directed test cases
        @(posedge clk) valid <= 1; a <= 9'sd100;  b <= 9'sd50;
        @(posedge clk) valid <= 1; a <= -9'sd100; b <= 9'sd50;
        @(posedge clk) valid <= 1; a <= 9'sd100;  b <= -9'sd100;
        @(posedge clk) valid <= 1; a <= -9'sd100; b <= -9'sd50;
        @(posedge clk) valid <= 1; a <= 9'sd50;   b <= 9'sd50;
        @(posedge clk) valid <= 1; a <= 9'sd50;   b <= 9'sd25;
        @(posedge clk) valid <= 1; a <= -9'sd50;  b <= -9'sd25;

        // Invalid inputs
        @(posedge clk) valid <= 0; a <= 9'sd20; b <= 9'sd30;
        @(posedge clk) valid <= 0; a <= 9'sd10; b <= 9'sd10;
        @(posedge clk) valid <= 0; a <= 9'sd5;  b <= 9'sd15;
        @(posedge clk) valid <= 0; a <= 9'sd0;  b <= 9'sd0;

        // Overflow test
        repeat (66) begin
            @(posedge clk)
            valid <= 1;
            a <= 9'sd255;
            b <= 9'sd255;
        end

        @(posedge clk)
        valid <= 0;
        a <= 0;
        b <= 0;

        // Reset
        @(posedge clk) rst_n <= 0;
        @(posedge clk) rst_n <= 1;

        // Random test cases
	repeat (100) begin
	    @(posedge clk);
	    valid <= 1;
	    a <= $urandom_range(-256,255);
	    b <= $urandom_range(-256,255);
	end

        repeat (4) @(posedge clk);
        $finish;
    end

endmodule

intMAC/mac.vcd
$date
	Sat Jul 11 06:05:42 2026
$end
$version
	Icarus Verilog
$end
$timescale
	1ps
$end
$scope module INT_mac_TB $end
$var wire 23 ! result [22:0] $end
$var wire 1 " overflow $end
$var wire 1 # out_valid $end
$var reg 9 $ a [8:0] $end
$var reg 9 % b [8:0] $end
$var reg 1 & clk $end
$var reg 1 ' rst_n $end
$var reg 1 ( valid $end
$scope module mac_inst $end
$var wire 9 ) i_a [8:0] $end
$var wire 9 * i_b [8:0] $end
$var wire 1 & i_clk $end
$var wire 1 ' i_rst_n $end
$var wire 1 ( i_valid $end
$var wire 23 + o_result [22:0] $end
$var wire 1 , overflow $end
$var wire 24 - extended_result [23:0] $end
$var reg 1 " o_overflow $end
$var reg 1 # o_valid $end
$var reg 18 . product [17:0] $end
$var reg 23 / result_reg [22:0] $end
$var reg 1 0 valid_0 $end
$upscope $end
$upscope $end
$enddefinitions $end
$comment Show the parameter values. $end
$dumpall
$end
#0
$dumpvars
00
b0 /
b0 .
b0 -
0,
b0 +
b0 *
b0 )
0(
0'
0&
b0 %
b0 $
0#
0"
b0 !
$end
#5000
1&
#10000
0&
#15000
1'
1&
#20000
0&
#25000
b110010 %
b110010 *
b1100100 $
b1100100 )
1(
1&
#30000
0&
#35000
b1001110001000 -
10
b1001110001000 .
b110011100 $
b110011100 )
1&
#40000
0&
#45000
b0 -
1#
b1001110001000 !
b1001110001000 +
b1001110001000 /
b111110110001111000 .
b110011100 %
b110011100 *
b1100100 $
b1100100 )
1&
#50000
0&
#55000
b111111111101100011110000 -
b111101100011110000 .
b0 !
b0 +
b0 /
b111001110 %
b111001110 *
b110011100 $
b110011100 )
1&
#60000
0&
#65000
0,
b111111111110110001111000 -
b11111111101100011110000 !
b11111111101100011110000 +
b11111111101100011110000 /
b1001110001000 .
b110010 %
b110010 *
b110010 $
b110010 )
1&
#70000
0&
#75000
b111111111111011000111100 -
b100111000100 .
b11111111110110001111000 !
b11111111110110001111000 +
b11111111110110001111000 /
b11001 %
b11001 *
1&
#80000
0&
#85000
b111111111111101100011110 -
b11111111111011000111100 !
b11111111111011000111100 +
b11111111111011000111100 /
b10011100010 .
b111100111 %
b111100111 *
b111001110 $
b111001110 )
1&
#90000
0&
#95000
b0 -
b11111111111101100011110 !
b11111111111101100011110 +
b11111111111101100011110 /
b11110 %
b11110 *
b10100 $
b10100 )
0(
1&
#100000
0&
#105000
0,
b10011100010 -
b0 !
b0 +
b0 /
00
b1010 %
b1010 *
b1010 $
b1010 )
1&
#110000
0&
#115000
0#
b1111 %
b1111 *
b101 $
b101 )
1&
#120000
0&
#125000
b0 %
b0 *
b0 $
b0 )
1&
#130000
0&
#135000
b11111111 %
b11111111 *
b11111111 $
b11111111 )
1(
1&
#140000
0&
#145000
b1111111000000001 -
10
b1111111000000001 .
1&
#150000
0&
#155000
b11111110000000010 -
1#
b1111111000000001 !
b1111111000000001 +
b1111111000000001 /
1&
#160000
0&
#165000
b101111101000000011 -
b11111110000000010 !
b11111110000000010 +
b11111110000000010 /
1&
#170000
0&
#175000
b111111100000000100 -
b101111101000000011 !
b101111101000000011 +
b101111101000000011 /
1&
#180000
0&
#185000
b1001111011000000101 -
b111111100000000100 !
b111111100000000100 +
b111111100000000100 /
1&
#190000
0&
#195000
b1011111010000000110 -
b1001111011000000101 !
b1001111011000000101 +
b1001111011000000101 /
1&
#200000
0&
#205000
b1101111001000000111 -
b1011111010000000110 !
b1011111010000000110 +
b1011111010000000110 /
1&
#210000
0&
#215000
b1111111000000001000 -
b1101111001000000111 !
b1101111001000000111 +
b1101111001000000111 /
1&
#220000
0&
#225000
b10001110111000001001 -
b1111111000000001000 !
b1111111000000001000 +
b1111111000000001000 /
1&
#230000
0&
#235000
b10011110110000001010 -
b10001110111000001001 !
b10001110111000001001 +
b10001110111000001001 /
1&
#240000
0&
#245000
b10101110101000001011 -
b10011110110000001010 !
b10011110110000001010 +
b10011110110000001010 /
1&
#250000
0&
#255000
b10111110100000001100 -
b10101110101000001011 !
b10101110101000001011 +
b10101110101000001011 /
1&
#260000
0&
#265000
b11001110011000001101 -
b10111110100000001100 !
b10111110100000001100 +
b10111110100000001100 /
1&
#270000
0&
#275000
b11011110010000001110 -
b11001110011000001101 !
b11001110011000001101 +
b11001110011000001101 /
1&
#280000
0&
#285000
b11101110001000001111 -
b11011110010000001110 !
b11011110010000001110 +
b11011110010000001110 /
1&
#290000
0&
#295000
b11111110000000010000 -
b11101110001000001111 !
b11101110001000001111 +
b11101110001000001111 /
1&
#300000
0&
#305000
b100001101111000010001 -
b11111110000000010000 !
b11111110000000010000 +
b11111110000000010000 /
1&
#310000
0&
#315000
b100011101110000010010 -
b100001101111000010001 !
b100001101111000010001 +
b100001101111000010001 /
1&
#320000
0&
#325000
b100101101101000010011 -
b100011101110000010010 !
b100011101110000010010 +
b100011101110000010010 /
1&
#330000
0&
#335000
b100111101100000010100 -
b100101101101000010011 !
b100101101101000010011 +
b100101101101000010011 /
1&
#340000
0&
#345000
b101001101011000010101 -
b100111101100000010100 !
b100111101100000010100 +
b100111101100000010100 /
1&
#350000
0&
#355000
b101011101010000010110 -
b101001101011000010101 !
b101001101011000010101 +
b101001101011000010101 /
1&
#360000
0&
#365000
b101101101001000010111 -
b101011101010000010110 !
b101011101010000010110 +
b101011101010000010110 /
1&
#370000
0&
#375000
b101111101000000011000 -
b101101101001000010111 !
b101101101001000010111 +
b101101101001000010111 /
1&
#380000
0&
#385000
b110001100111000011001 -
b101111101000000011000 !
b101111101000000011000 +
b101111101000000011000 /
1&
#390000
0&
#395000
b110011100110000011010 -
b110001100111000011001 !
b110001100111000011001 +
b110001100111000011001 /
1&
#400000
0&
#405000
b110101100101000011011 -
b110011100110000011010 !
b110011100110000011010 +
b110011100110000011010 /
1&
#410000
0&
#415000
b110111100100000011100 -
b110101100101000011011 !
b110101100101000011011 +
b110101100101000011011 /
1&
#420000
0&
#425000
b111001100011000011101 -
b110111100100000011100 !
b110111100100000011100 +
b110111100100000011100 /
1&
#430000
0&
#435000
b111011100010000011110 -
b111001100011000011101 !
b111001100011000011101 +
b111001100011000011101 /
1&
#440000
0&
#445000
b111101100001000011111 -
b111011100010000011110 !
b111011100010000011110 +
b111011100010000011110 /
1&
#450000
0&
#455000
b111111100000000100000 -
b111101100001000011111 !
b111101100001000011111 +
b111101100001000011111 /
1&
#460000
0&
#465000
b1000001011111000100001 -
b111111100000000100000 !
b111111100000000100000 +
b111111100000000100000 /
1&
#470000
0&
#475000
b1000011011110000100010 -
b1000001011111000100001 !
b1000001011111000100001 +
b1000001011111000100001 /
1&
#480000
0&
#485000
b1000101011101000100011 -
b1000011011110000100010 !
b1000011011110000100010 +
b1000011011110000100010 /
1&
#490000
0&
#495000
b1000111011100000100100 -
b1000101011101000100011 !
b1000101011101000100011 +
b1000101011101000100011 /
1&
#500000
0&
#505000
b1001001011011000100101 -
b1000111011100000100100 !
b1000111011100000100100 +
b1000111011100000100100 /
1&
#510000
0&
#515000
b1001011011010000100110 -
b1001001011011000100101 !
b1001001011011000100101 +
b1001001011011000100101 /
1&
#520000
0&
#525000
b1001101011001000100111 -
b1001011011010000100110 !
b1001011011010000100110 +
b1001011011010000100110 /
1&
#530000
0&
#535000
b1001111011000000101000 -
b1001101011001000100111 !
b1001101011001000100111 +
b1001101011001000100111 /
1&
#540000
0&
#545000
b1010001010111000101001 -
b1001111011000000101000 !
b1001111011000000101000 +
b1001111011000000101000 /
1&
#550000
0&
#555000
b1010011010110000101010 -
b1010001010111000101001 !
b1010001010111000101001 +
b1010001010111000101001 /
1&
#560000
0&
#565000
b1010101010101000101011 -
b1010011010110000101010 !
b1010011010110000101010 +
b1010011010110000101010 /
1&
#570000
0&
#575000
b1010111010100000101100 -
b1010101010101000101011 !
b1010101010101000101011 +
b1010101010101000101011 /
1&
#580000
0&
#585000
b1011001010011000101101 -
b1010111010100000101100 !
b1010111010100000101100 +
b1010111010100000101100 /
1&
#590000
0&
#595000
b1011011010010000101110 -
b1011001010011000101101 !
b1011001010011000101101 +
b1011001010011000101101 /
1&
#600000
0&
#605000
b1011101010001000101111 -
b1011011010010000101110 !
b1011011010010000101110 +
b1011011010010000101110 /
1&
#610000
0&
#615000
b1011111010000000110000 -
b1011101010001000101111 !
b1011101010001000101111 +
b1011101010001000101111 /
1&
#620000
0&
#625000
b1100001001111000110001 -
b1011111010000000110000 !
b1011111010000000110000 +
b1011111010000000110000 /
1&
#630000
0&
#635000
b1100011001110000110010 -
b1100001001111000110001 !
b1100001001111000110001 +
b1100001001111000110001 /
1&
#640000
0&
#645000
b1100101001101000110011 -
b1100011001110000110010 !
b1100011001110000110010 +
b1100011001110000110010 /
1&
#650000
0&
#655000
b1100111001100000110100 -
b1100101001101000110011 !
b1100101001101000110011 +
b1100101001101000110011 /
1&
#660000
0&
#665000
b1101001001011000110101 -
b1100111001100000110100 !
b1100111001100000110100 +
b1100111001100000110100 /
1&
#670000
0&
#675000
b1101011001010000110110 -
b1101001001011000110101 !
b1101001001011000110101 +
b1101001001011000110101 /
1&
#680000
0&
#685000
b1101101001001000110111 -
b1101011001010000110110 !
b1101011001010000110110 +
b1101011001010000110110 /
1&
#690000
0&
#695000
b1101111001000000111000 -
b1101101001001000110111 !
b1101101001001000110111 +
b1101101001001000110111 /
1&
#700000
0&
#705000
b1110001000111000111001 -
b1101111001000000111000 !
b1101111001000000111000 +
b1101111001000000111000 /
1&
#710000
0&
#715000
b1110011000110000111010 -
b1110001000111000111001 !
b1110001000111000111001 +
b1110001000111000111001 /
1&
#720000
0&
#725000
b1110101000101000111011 -
b1110011000110000111010 !
b1110011000110000111010 +
b1110011000110000111010 /
1&
#730000
0&
#735000
b1110111000100000111100 -
b1110101000101000111011 !
b1110101000101000111011 +
b1110101000101000111011 /
1&
#740000
0&
#745000
b1111001000011000111101 -
b1110111000100000111100 !
b1110111000100000111100 +
b1110111000100000111100 /
1&
#750000
0&
#755000
b1111011000010000111110 -
b1111001000011000111101 !
b1111001000011000111101 +
b1111001000011000111101 /
1&
#760000
0&
#765000
b1111101000001000111111 -
b1111011000010000111110 !
b1111011000010000111110 +
b1111011000010000111110 /
1&
#770000
0&
#775000
b1111111000000001000000 -
b1111101000001000111111 !
b1111101000001000111111 +
b1111101000001000111111 /
1&
#780000
0&
#785000
1,
b10000000111111001000001 -
b1111111000000001000000 !
b1111111000000001000000 +
b1111111000000001000000 /
1&
#790000
0&
#795000
0,
b110000010111110001000010 -
1"
b10000000111111001000001 !
b10000000111111001000001 +
b10000000111111001000001 /
b0 %
b0 *
b0 $
b0 )
0(
1&
#800000
0&
#805000
0,
b0 -
b0 .
0"
b0 !
b0 +
b0 /
0#
00
0'
1&
#810000
0&
#815000
1'
1&
#820000
0&
#825000
b11111111 %
b11111111 *
b100000000 $
b100000000 )
1(
1&
#830000
0&
#835000
b111111110000000100000000 -
10
b110000000100000000 .
b11111111 $
b11111111 )
1&
#840000
0&
#845000
0,
b111111111111111100000001 -
b1111111000000001 .
1#
b11111110000000100000000 !
b11111110000000100000000 +
b11111110000000100000000 /
b100000000 %
b100000000 *
b100000000 $
b100000000 )
1&
#850000
0&
#855000
b1111111100000001 -
b11111111111111100000001 !
b11111111111111100000001 +
b11111111111111100000001 /
b10000000000000000 .
b11111111 %
b11111111 *
b11111111 $
b11111111 )
1&
#860000
0&
#865000
0,
b11111110100000010 -
b1111111000000001 .
b1111111100000001 !
b1111111100000001 +
b1111111100000001 /
b100000000 %
b100000000 *
b100000000 $
b100000000 )
1&
#870000
0&
#875000
b101111110100000010 -
b11111110100000010 !
b11111110100000010 +
b11111110100000010 /
b10000000000000000 .
1&
#880000
0&
#885000
b111111110100000010 -
b101111110100000010 !
b101111110100000010 +
b101111110100000010 /
1&
#890000
0&
#895000
b1001111110100000010 -
b111111110100000010 !
b111111110100000010 +
b111111110100000010 /
b11111111 %
b11111111 *
1&
#900000
0&
#905000
b111111111000000010 -
b110000000100000000 .
b1001111110100000010 !
b1001111110100000010 +
b1001111110100000010 /
b11111111 $
b11111111 )
1&
#910000
0&
#915000
b1001111110000000011 -
b111111111000000010 !
b111111111000000010 +
b111111111000000010 /
b1111111000000001 .
b100000000 $
b100000000 )
1&
#920000
0&
#925000
b111111110100000011 -
b110000000100000000 .
b1001111110000000011 !
b1001111110000000011 +
b1001111110000000011 /
b100000000 %
b100000000 *
b11111111 $
b11111111 )
1&
#930000
0&
#935000
b101111111000000011 -
b111111110100000011 !
b111111110100000011 +
b111111110100000011 /
b11111111 %
b11111111 *
b100000000 $
b100000000 )
1&
#940000
0&
#945000
b11111111100000011 -
b101111111000000011 !
b101111111000000011 +
b101111111000000011 /
b11111111 $
b11111111 )
1&
#950000
0&
#955000
b101111110100000100 -
b11111111100000011 !
b11111111100000011 +
b11111111100000011 /
b1111111000000001 .
b100000000 $
b100000000 )
1&
#960000
0&
#965000
b11111111000000100 -
b110000000100000000 .
b101111110100000100 !
b101111110100000100 +
b101111110100000100 /
b11111111 $
b11111111 )
1&
#970000
0&
#975000
b101111110000000101 -
b11111111000000100 !
b11111111000000100 +
b11111111000000100 /
b1111111000000001 .
b100000000 %
b100000000 *
1&
#980000
0&
#985000
b11111110100000101 -
b110000000100000000 .
b101111110000000101 !
b101111110000000101 +
b101111110000000101 /
1&
#990000
0&
#995000
b1111111000000101 -
b11111110100000101 !
b11111110100000101 +
b11111110100000101 /
b11111111 %
b11111111 *
b100000000 $
b100000000 )
1&
#1000000
0&
#1005000
b111111111111111100000101 -
b1111111000000101 !
b1111111000000101 +
b1111111000000101 /
b11111111 $
b11111111 )
1&
#1010000
0&
#1015000
b1111110100000110 -
b11111111111111100000101 !
b11111111111111100000101 +
b11111111111111100000101 /
b1111111000000001 .
1&
#1020000
0&
#1025000
0,
b11111101100000111 -
b1111110100000110 !
b1111110100000110 +
b1111110100000110 /
b100000000 $
b100000000 )
1&
#1030000
0&
#1035000
b1111110000000111 -
b11111101100000111 !
b11111101100000111 +
b11111101100000111 /
b110000000100000000 .
b11111111 $
b11111111 )
1&
#1040000
0&
#1045000
b11111101000001000 -
b1111111000000001 .
b1111110000000111 !
b1111110000000111 +
b1111110000000111 /
b100000000 $
b100000000 )
1&
#1050000
0&
#1055000
b1111101100001000 -
b11111101000001000 !
b11111101000001000 +
b11111101000001000 /
b110000000100000000 .
b100000000 %
b100000000 *
1&
#1060000
0&
#1065000
b11111101100001000 -
b10000000000000000 .
b1111101100001000 !
b1111101100001000 +
b1111101100001000 /
b11111111 %
b11111111 *
b11111111 $
b11111111 )
1&
#1070000
0&
#1075000
b101111100100001001 -
b11111101100001000 !
b11111101100001000 +
b11111101100001000 /
b1111111000000001 .
b100000000 %
b100000000 *
b100000000 $
b100000000 )
1&
#1080000
0&
#1085000
b111111100100001001 -
b10000000000000000 .
b101111100100001001 !
b101111100100001001 +
b101111100100001001 /
b11111111 %
b11111111 *
1&
#1090000
0&
#1095000
b101111101000001001 -
b111111100100001001 !
b111111100100001001 +
b111111100100001001 /
b110000000100000000 .
1&
#1100000
0&
#1105000
b11111101100001001 -
b101111101000001001 !
b101111101000001001 +
b101111101000001001 /
b100000000 %
b100000000 *
1&
#1110000
0&
#1115000
b101111101100001001 -
b11111101100001001 !
b11111101100001001 +
b11111101100001001 /
b10000000000000000 .
1&
#1120000
0&
#1125000
b111111101100001001 -
b101111101100001001 !
b101111101100001001 +
b101111101100001001 /
b11111111 $
b11111111 )
1&
#1130000
0&
#1135000
b101111110000001001 -
b111111101100001001 !
b111111101100001001 +
b111111101100001001 /
b110000000100000000 .
b11111111 %
b11111111 *
1&
#1140000
0&
#1145000
b111111101000001010 -
b1111111000000001 .
b101111110000001001 !
b101111110000001001 +
b101111110000001001 /
b100000000 %
b100000000 *
b100000000 $
b100000000 )
1&
#1150000
0&
#1155000
b1001111101000001010 -
b111111101000001010 !
b111111101000001010 +
b111111101000001010 /
b10000000000000000 .
b11111111 $
b11111111 )
1&
#1160000
0&
#1165000
b111111101100001010 -
b110000000100000000 .
b1001111101000001010 !
b1001111101000001010 +
b1001111101000001010 /
1&
#1170000
0&
#1175000
b101111110000001010 -
b111111101100001010 !
b111111101100001010 +
b111111101100001010 /
b100000000 $
b100000000 )
1&
#1180000
0&
#1185000
b111111110000001010 -
b10000000000000000 .
b101111110000001010 !
b101111110000001010 +
b101111110000001010 /
1&
#1190000
0&
#1195000
b1001111110000001010 -
b111111110000001010 !
b111111110000001010 +
b111111110000001010 /
1&
#1200000
0&
#1205000
b1011111110000001010 -
b1001111110000001010 !
b1001111110000001010 +
b1001111110000001010 /
b11111111 %
b11111111 *
1&
#1210000
0&
#1215000
b1001111110100001010 -
b1011111110000001010 !
b1011111110000001010 +
b1011111110000001010 /
b110000000100000000 .
b11111111 $
b11111111 )
1&
#1220000
0&
#1225000
b1011111101100001011 -
b1111111000000001 .
b1001111110100001010 !
b1001111110100001010 +
b1001111110100001010 /
b100000000 %
b100000000 *
1&
#1230000
0&
#1235000
b1001111110000001011 -
b1011111101100001011 !
b1011111101100001011 +
b1011111101100001011 /
b110000000100000000 .
b11111111 %
b11111111 *
1&
#1240000
0&
#1245000
b1011111101000001100 -
b1111111000000001 .
b1001111110000001011 !
b1001111110000001011 +
b1001111110000001011 /
1&
#1250000
0&
#1255000
b1101111100000001101 -
b1011111101000001100 !
b1011111101000001100 +
b1011111101000001100 /
b100000000 %
b100000000 *
b100000000 $
b100000000 )
1&
#1260000
0&
#1265000
b1111111100000001101 -
b10000000000000000 .
b1101111100000001101 !
b1101111100000001101 +
b1101111100000001101 /
b11111111 $
b11111111 )
1&
#1270000
0&
#1275000
b1101111100100001101 -
b1111111100000001101 !
b1111111100000001101 +
b1111111100000001101 /
b110000000100000000 .
1&
#1280000
0&
#1285000
b1011111101000001101 -
b1101111100100001101 !
b1101111100100001101 +
b1101111100100001101 /
b11111111 %
b11111111 *
b100000000 $
b100000000 )
1&
#1290000
0&
#1295000
b1001111101100001101 -
b1011111101000001101 !
b1011111101000001101 +
b1011111101000001101 /
b100000000 %
b100000000 *
1&
#1300000
0&
#1305000
b1011111101100001101 -
b10000000000000000 .
b1001111101100001101 !
b1001111101100001101 +
b1001111101100001101 /
b11111111 %
b11111111 *
1&
#1310000
0&
#1315000
b1001111110000001101 -
b1011111101100001101 !
b1011111101100001101 +
b1011111101100001101 /
b110000000100000000 .
1&
#1320000
0&
#1325000
b111111110100001101 -
b1001111110000001101 !
b1001111110000001101 +
b1001111110000001101 /
b100000000 %
b100000000 *
1&
#1330000
0&
#1335000
b1001111110100001101 -
b111111110100001101 !
b111111110100001101 +
b111111110100001101 /
b10000000000000000 .
b11111111 $
b11111111 )
1&
#1340000
0&
#1345000
b111111111000001101 -
b110000000100000000 .
b1001111110100001101 !
b1001111110100001101 +
b1001111110100001101 /
b11111111 %
b11111111 *
b100000000 $
b100000000 )
1&
#1350000
0&
#1355000
b101111111100001101 -
b111111111000001101 !
b111111111000001101 +
b111111111000001101 /
b11111111 $
b11111111 )
1&
#1360000
0&
#1365000
b111111110100001110 -
b1111111000000001 .
b101111111100001101 !
b101111111100001101 +
b101111111100001101 /
b100000000 $
b100000000 )
1&
#1370000
0&
#1375000
b101111111000001110 -
b111111110100001110 !
b111111110100001110 +
b111111110100001110 /
b110000000100000000 .
1&
#1380000
0&
#1385000
b11111111100001110 -
b101111111000001110 !
b101111111000001110 +
b101111111000001110 /
b11111111 $
b11111111 )
1&
#1390000
0&
#1395000
b101111110100001111 -
b11111111100001110 !
b11111111100001110 +
b11111111100001110 /
b1111111000000001 .
b100000000 %
b100000000 *
1&
#1400000
0&
#1405000
b11111111000001111 -
b110000000100000000 .
b101111110100001111 !
b101111110100001111 +
b101111110100001111 /
b11111111 %
b11111111 *
b100000000 $
b100000000 )
1&
#1410000
0&
#1415000
b1111111100001111 -
b11111111000001111 !
b11111111000001111 +
b11111111000001111 /
b100000000 %
b100000000 *
b11111111 $
b11111111 )
1&
#1420000
0&
#1425000
b1111 -
b1111111100001111 !
b1111111100001111 +
b1111111100001111 /
b11111111 %
b11111111 *
b100000000 $
b100000000 )
1&
#1430000
0&
#1435000
b111111110000000100001111 -
b1111 !
b1111 +
b1111 /
b11111111 $
b11111111 )
1&
#1440000
0&
#1445000
0,
b111111111111111100010000 -
b1111111000000001 .
b11111110000000100001111 !
b11111110000000100001111 +
b11111110000000100001111 /
1&
#1450000
0&
#1455000
b1111110100010001 -
b11111111111111100010000 !
b11111111111111100010000 +
b11111111111111100010000 /
b100000000 %
b100000000 *
b100000000 $
b100000000 )
1&
#1460000
0&
#1465000
0,
b11111110100010001 -
b10000000000000000 .
b1111110100010001 !
b1111110100010001 +
b1111110100010001 /
b11111111 $
b11111111 )
1&
#1470000
0&
#1475000
b1111111000010001 -
b11111110100010001 !
b11111110100010001 +
b11111110100010001 /
b110000000100000000 .
b100000000 $
b100000000 )
1&
#1480000
0&
#1485000
b11111111000010001 -
b10000000000000000 .
b1111111000010001 !
b1111111000010001 +
b1111111000010001 /
b11111111 %
b11111111 *
1&
#1490000
0&
#1495000
b1111111100010001 -
b11111111000010001 !
b11111111000010001 +
b11111111000010001 /
b110000000100000000 .
b11111111 $
b11111111 )
1&
#1500000
0&
#1505000
b11111110100010010 -
b1111111000000001 .
b1111111100010001 !
b1111111100010001 +
b1111111100010001 /
b100000000 %
b100000000 *
b100000000 $
b100000000 )
1&
#1510000
0&
#1515000
b101111110100010010 -
b11111110100010010 !
b11111110100010010 +
b11111110100010010 /
b10000000000000000 .
b11111111 %
b11111111 *
b11111111 $
b11111111 )
1&
#1520000
0&
#1525000
b111111101100010011 -
b1111111000000001 .
b101111110100010010 !
b101111110100010010 +
b101111110100010010 /
b100000000 $
b100000000 )
1&
#1530000
0&
#1535000
b101111110000010011 -
b111111101100010011 !
b111111101100010011 +
b111111101100010011 /
b110000000100000000 .
1&
#1540000
0&
#1545000
b11111110100010011 -
b101111110000010011 !
b101111110000010011 +
b101111110000010011 /
b100000000 %
b100000000 *
1&
#1550000
0&
#1555000
b101111110100010011 -
b11111110100010011 !
b11111110100010011 +
b11111110100010011 /
b10000000000000000 .
b11111111 %
b11111111 *
b11111111 $
b11111111 )
1&
#1560000
0&
#1565000
b111111101100010100 -
b1111111000000001 .
b101111110100010011 !
b101111110100010011 +
b101111110100010011 /
b100000000 $
b100000000 )
1&
#1570000
0&
#1575000
b101111110000010100 -
b111111101100010100 !
b111111101100010100 +
b111111101100010100 /
b110000000100000000 .
1&
#1580000
0&
#1585000
b11111110100010100 -
b101111110000010100 !
b101111110000010100 +
b101111110000010100 /
b100000000 %
b100000000 *
b11111111 $
b11111111 )
1&
#1590000
0&
#1595000
b1111111000010100 -
b11111110100010100 !
b11111110100010100 +
b11111110100010100 /
b100000000 $
b100000000 )
1&
#1600000
0&
#1605000
b11111111000010100 -
b10000000000000000 .
b1111111000010100 !
b1111111000010100 +
b1111111000010100 /
b11111111 $
b11111111 )
1&
#1610000
0&
#1615000
b1111111100010100 -
b11111111000010100 !
b11111111000010100 +
b11111111000010100 /
b110000000100000000 .
b100000000 $
b100000000 )
1&
#1620000
0&
#1625000
b11111111100010100 -
b10000000000000000 .
b1111111100010100 !
b1111111100010100 +
b1111111100010100 /
b11111111 $
b11111111 )
1&
#1630000
0&
#1635000
b10000000000010100 -
b11111111100010100 !
b11111111100010100 +
b11111111100010100 /
b110000000100000000 .
b11111111 %
b11111111 *
b100000000 $
b100000000 )
1&
#1640000
0&
#1645000
b100010100 -
b10000000000010100 !
b10000000000010100 +
b10000000000010100 /
b11111111 $
b11111111 )
1&
#1650000
0&
#1655000
b1111111100010101 -
b100010100 !
b100010100 +
b100010100 /
b1111111000000001 .
b100000000 %
b100000000 *
1&
#1660000
0&
#1665000
b10101 -
b110000000100000000 .
b1111111100010101 !
b1111111100010101 +
b1111111100010101 /
1&
#1670000
0&
#1675000
b111111110000000100010101 -
b10101 !
b10101 +
b10101 /
1&
#1680000
0&
#1685000
0,
b111111100000001000010101 -
b11111110000000100010101 !
b11111110000000100010101 +
b11111110000000100010101 /
b11111111 %
b11111111 *
1&
#1690000
0&
#1695000
b111111110000000000010110 -
b11111100000001000010101 !
b11111100000001000010101 +
b11111100000001000010101 /
b1111111000000001 .
b100000000 $
b100000000 )
1&
#1700000
0&
#1705000
b111111100000000100010110 -
b110000000100000000 .
b11111110000000000010110 !
b11111110000000000010110 +
b11111110000000000010110 /
b100000000 %
b100000000 *
b11111111 $
b11111111 )
1&
#1710000
0&
#1715000
b111111010000001000010110 -
b11111100000000100010110 !
b11111100000000100010110 +
b11111100000000100010110 /
b100000000 $
b100000000 )
1&
#1720000
0&
#1725000
b111111100000001000010110 -
b10000000000000000 .
b11111010000001000010110 !
b11111010000001000010110 +
b11111010000001000010110 /
b11111111 %
b11111111 *
1&
#1730000
0&
#1735000
b111111010000001100010110 -
b11111100000001000010110 !
b11111100000001000010110 +
b11111100000001000010110 /
b110000000100000000 .
b100000000 %
b100000000 *
b11111111 $
b11111111 )
1&
#1740000
0&
#1745000
b111111000000010000010110 -
b11111010000001100010110 !
b11111010000001100010110 +
b11111010000001100010110 /
b100000000 $
b100000000 )
1&
#1750000
0&
#1755000
b111111010000010000010110 -
b11111000000010000010110 !
b11111000000010000010110 +
b11111000000010000010110 /
b10000000000000000 .
b11111111 %
b11111111 *
1&
#1760000
0&
#1765000
b111111000000010100010110 -
b110000000100000000 .
b11111010000010000010110 !
b11111010000010000010110 +
b11111010000010000010110 /
b100000000 %
b100000000 *
1&
#1770000
0&
#1775000
b111111010000010100010110 -
b11111000000010100010110 !
b11111000000010100010110 +
b11111000000010100010110 /
b10000000000000000 .
1&
#1780000
0&
#1785000
b111111100000010100010110 -
b11111010000010100010110 !
b11111010000010100010110 +
b11111010000010100010110 /
b11111111 %
b11111111 *
1&
#1790000
0&
